{
  "region": "lake-country",
  "updatedAt": "2026-06-18T00:32:22.188Z",
  "samples": [
    {
      "at": "2026-05-12T12:00:00.000Z",
      "marketAverage": 201.2,
      "stationCount": 7
    },
    {
      "at": "2026-05-13T12:00:00.000Z",
      "marketAverage": 199.2,
      "stationCount": 7
    },
    {
      "at": "2026-05-14T12:00:00.000Z",
      "marketAverage": 194.6,
      "stationCount": 8
    },
    {
      "at": "2026-05-15T12:00:00.000Z",
      "marketAverage": 190.9,
      "stationCount": 7
    },
    {
      "at": "2026-05-16T12:00:00.000Z",
      "marketAverage": 187.2,
      "stationCount": 7
    },
    {
      "at": "2026-05-17T12:00:00.000Z",
      "marketAverage": 185,
      "stationCount": 8
    },
    {
      "at": "2026-05-18T12:00:00.000Z",
      "marketAverage": 180.1,
      "stationCount": 8
    },
    {
      "at": "2026-05-19T05:15:40.933Z",
      "marketAverage": 178.2,
      "stationCount": 8
    },
    {
      "at": "2026-05-19T12:00:00.000Z",
      "marketAverage": 178.2,
      "stationCount": 8
    },
    {
      "at": "2026-05-19T16:29:34.863Z",
      "marketAverage": 176.9,
      "stationCount": 8
    },
    {
      "at": "2026-05-19T19:19:21.386Z",
      "marketAverage": 179.2,
      "stationCount": 8
    },
    {
      "at": "2026-05-19T21:31:42.364Z",
      "marketAverage": 179.4,
      "stationCount": 8
    },
    {
      "at": "2026-05-19T23:21:54.507Z",
      "marketAverage": 179.2,
      "stationCount": 8
    },
    {
      "at": "2026-05-20T04:16:29.291Z",
      "marketAverage": 178.2,
      "stationCount": 8
    },
    {
      "at": "2026-05-20T16:43:22.629Z",
      "marketAverage": 191.2,
      "stationCount": 8
    },
    {
      "at": "2026-05-20T19:36:27.886Z",
      "marketAverage": 196.9,
      "stationCount": 8
    },
    {
      "at": "2026-05-20T22:05:53.113Z",
      "marketAverage": 199.6,
      "stationCount": 7
    },
    {
      "at": "2026-05-21T00:16:42.941Z",
      "marketAverage": 196.9,
      "stationCount": 8
    },
    {
      "at": "2026-05-21T05:18:10.919Z",
      "marketAverage": 196.9,
      "stationCount": 8
    },
    {
      "at": "2026-05-21T16:22:17.269Z",
      "marketAverage": 196.7,
      "stationCount": 8
    },
    {
      "at": "2026-05-21T19:04:50.086Z",
      "marketAverage": 196.2,
      "stationCount": 8
    },
    {
      "at": "2026-05-21T21:50:05.185Z",
      "marketAverage": 196.4,
      "stationCount": 8
    },
    {
      "at": "2026-05-21T23:08:47.535Z",
      "marketAverage": 196,
      "stationCount": 8
    },
    {
      "at": "2026-05-22T04:14:06.851Z",
      "marketAverage": 195.7,
      "stationCount": 8
    },
    {
      "at": "2026-05-22T15:53:15.211Z",
      "marketAverage": 195.7,
      "stationCount": 8
    },
    {
      "at": "2026-05-22T18:00:18.753Z",
      "marketAverage": 195.7,
      "stationCount": 8
    },
    {
      "at": "2026-05-22T20:12:09.891Z",
      "marketAverage": 194.5,
      "stationCount": 8
    },
    {
      "at": "2026-05-22T22:24:02.346Z",
      "marketAverage": 194.5,
      "stationCount": 8
    },
    {
      "at": "2026-05-23T04:49:07.094Z",
      "marketAverage": 194.3,
      "stationCount": 8
    },
    {
      "at": "2026-05-23T14:44:12.719Z",
      "marketAverage": 194.3,
      "stationCount": 8
    },
    {
      "at": "2026-05-23T16:13:22.730Z",
      "marketAverage": 194.3,
      "stationCount": 8
    },
    {
      "at": "2026-05-23T18:17:03.178Z",
      "marketAverage": 194.3,
      "stationCount": 8
    },
    {
      "at": "2026-05-23T20:21:12.710Z",
      "marketAverage": 193.5,
      "stationCount": 7
    },
    {
      "at": "2026-05-23T22:10:29.352Z",
      "marketAverage": 193.3,
      "stationCount": 7
    },
    {
      "at": "2026-05-23T23:09:44.399Z",
      "marketAverage": 193.3,
      "stationCount": 7
    },
    {
      "at": "2026-05-24T04:11:04.360Z",
      "marketAverage": 193.2,
      "stationCount": 7
    },
    {
      "at": "2026-05-24T14:34:44.973Z",
      "marketAverage": 193.7,
      "stationCount": 8
    },
    {
      "at": "2026-05-24T16:17:24.088Z",
      "marketAverage": 193.7,
      "stationCount": 8
    },
    {
      "at": "2026-05-24T18:08:32.671Z",
      "marketAverage": 193.7,
      "stationCount": 8
    },
    {
      "at": "2026-05-24T20:19:31.323Z",
      "marketAverage": 193.7,
      "stationCount": 8
    },
    {
      "at": "2026-05-24T22:02:48.555Z",
      "marketAverage": 193.7,
      "stationCount": 8
    },
    {
      "at": "2026-05-24T23:22:16.431Z",
      "marketAverage": 192.5,
      "stationCount": 8
    },
    {
      "at": "2026-05-25T04:22:49.319Z",
      "marketAverage": 191.8,
      "stationCount": 8
    },
    {
      "at": "2026-05-25T15:58:08.312Z",
      "marketAverage": 187,
      "stationCount": 8
    },
    {
      "at": "2026-05-25T17:57:11.480Z",
      "marketAverage": 186,
      "stationCount": 8
    },
    {
      "at": "2026-05-25T23:20:52.903Z",
      "marketAverage": 184.7,
      "stationCount": 8
    },
    {
      "at": "2026-05-26T04:09:42.383Z",
      "marketAverage": 183.2,
      "stationCount": 8
    },
    {
      "at": "2026-05-26T16:49:24.503Z",
      "marketAverage": 183.5,
      "stationCount": 8
    },
    {
      "at": "2026-05-26T19:35:47.684Z",
      "marketAverage": 184,
      "stationCount": 8
    },
    {
      "at": "2026-05-26T21:55:21.481Z",
      "marketAverage": 184,
      "stationCount": 8
    },
    {
      "at": "2026-05-26T23:19:22.819Z",
      "marketAverage": 182.7,
      "stationCount": 8
    },
    {
      "at": "2026-05-27T16:41:13.445Z",
      "marketAverage": 185.8,
      "stationCount": 8
    },
    {
      "at": "2026-05-27T19:40:21.162Z",
      "marketAverage": 185.8,
      "stationCount": 8
    },
    {
      "at": "2026-05-27T22:09:49.561Z",
      "marketAverage": 184.8,
      "stationCount": 8
    },
    {
      "at": "2026-05-28T00:04:45.135Z",
      "marketAverage": 182,
      "stationCount": 8
    },
    {
      "at": "2026-05-28T05:26:07.466Z",
      "marketAverage": 183.3,
      "stationCount": 8
    },
    {
      "at": "2026-05-28T17:11:13.366Z",
      "marketAverage": 184.5,
      "stationCount": 8
    },
    {
      "at": "2026-05-28T19:52:10.603Z",
      "marketAverage": 184.5,
      "stationCount": 8
    },
    {
      "at": "2026-05-28T22:12:51.836Z",
      "marketAverage": 183.5,
      "stationCount": 8
    },
    {
      "at": "2026-05-29T04:22:43.037Z",
      "marketAverage": 182,
      "stationCount": 8
    },
    {
      "at": "2026-05-29T16:49:44.153Z",
      "marketAverage": 180.9,
      "stationCount": 8
    },
    {
      "at": "2026-05-29T19:43:59.104Z",
      "marketAverage": 180.9,
      "stationCount": 8
    },
    {
      "at": "2026-05-29T21:58:27.103Z",
      "marketAverage": 175.2,
      "stationCount": 8
    },
    {
      "at": "2026-05-29T23:25:11.653Z",
      "marketAverage": 175,
      "stationCount": 8
    },
    {
      "at": "2026-05-30T04:02:28.312Z",
      "marketAverage": 174.7,
      "stationCount": 8
    },
    {
      "at": "2026-05-30T14:49:50.144Z",
      "marketAverage": 173.9,
      "stationCount": 8
    },
    {
      "at": "2026-05-30T16:11:22.355Z",
      "marketAverage": 173.9,
      "stationCount": 8
    },
    {
      "at": "2026-05-30T18:13:34.701Z",
      "marketAverage": 173.9,
      "stationCount": 8
    },
    {
      "at": "2026-05-30T20:22:05.282Z",
      "marketAverage": 173.9,
      "stationCount": 8
    },
    {
      "at": "2026-05-30T22:15:05.941Z",
      "marketAverage": 173.9,
      "stationCount": 8
    },
    {
      "at": "2026-05-31T00:05:53.394Z",
      "marketAverage": 173.9,
      "stationCount": 8
    },
    {
      "at": "2026-05-31T05:31:48.733Z",
      "marketAverage": 173.2,
      "stationCount": 8
    },
    {
      "at": "2026-05-31T16:20:05.918Z",
      "marketAverage": 172.9,
      "stationCount": 8
    },
    {
      "at": "2026-05-31T18:10:31.360Z",
      "marketAverage": 172.9,
      "stationCount": 8
    },
    {
      "at": "2026-05-31T20:22:06.927Z",
      "marketAverage": 172.9,
      "stationCount": 8
    },
    {
      "at": "2026-05-31T22:09:30.341Z",
      "marketAverage": 172.9,
      "stationCount": 8
    },
    {
      "at": "2026-06-01T00:21:25.929Z",
      "marketAverage": 172.7,
      "stationCount": 8
    },
    {
      "at": "2026-06-01T06:12:48.332Z",
      "marketAverage": 172.7,
      "stationCount": 8
    },
    {
      "at": "2026-06-01T18:53:14.609Z",
      "marketAverage": 170.9,
      "stationCount": 8
    },
    {
      "at": "2026-06-01T22:27:00.177Z",
      "marketAverage": 169.2,
      "stationCount": 8
    },
    {
      "at": "2026-06-02T00:26:31.522Z",
      "marketAverage": 168.9,
      "stationCount": 8
    },
    {
      "at": "2026-06-02T06:00:12.204Z",
      "marketAverage": 166.4,
      "stationCount": 7
    },
    {
      "at": "2026-06-02T17:36:56.431Z",
      "marketAverage": 172.5,
      "stationCount": 8
    },
    {
      "at": "2026-06-02T21:06:16.917Z",
      "marketAverage": 176.2,
      "stationCount": 8
    },
    {
      "at": "2026-06-03T04:57:22.803Z",
      "marketAverage": 175.2,
      "stationCount": 8
    },
    {
      "at": "2026-06-03T18:08:51.064Z",
      "marketAverage": 174.9,
      "stationCount": 8
    },
    {
      "at": "2026-06-03T22:02:31.014Z",
      "marketAverage": 177,
      "stationCount": 8
    },
    {
      "at": "2026-06-03T23:54:15.396Z",
      "marketAverage": 176.8,
      "stationCount": 8
    },
    {
      "at": "2026-06-04T04:47:18.890Z",
      "marketAverage": 175.8,
      "stationCount": 8
    },
    {
      "at": "2026-06-04T16:34:16.292Z",
      "marketAverage": 174.8,
      "stationCount": 8
    },
    {
      "at": "2026-06-04T19:36:03.183Z",
      "marketAverage": 173.9,
      "stationCount": 8
    },
    {
      "at": "2026-06-04T21:49:48.426Z",
      "marketAverage": 174.2,
      "stationCount": 8
    },
    {
      "at": "2026-06-04T23:23:11.913Z",
      "marketAverage": 174.5,
      "stationCount": 7
    },
    {
      "at": "2026-06-05T04:28:20.335Z",
      "marketAverage": 173.5,
      "stationCount": 7
    },
    {
      "at": "2026-06-05T16:02:03.103Z",
      "marketAverage": 173.5,
      "stationCount": 7
    },
    {
      "at": "2026-06-05T18:10:13.933Z",
      "marketAverage": 173.5,
      "stationCount": 7
    },
    {
      "at": "2026-06-05T20:59:24.146Z",
      "marketAverage": 173,
      "stationCount": 7
    },
    {
      "at": "2026-06-05T22:31:08.655Z",
      "marketAverage": 172.8,
      "stationCount": 7
    },
    {
      "at": "2026-06-06T00:17:14.587Z",
      "marketAverage": 172.5,
      "stationCount": 7
    },
    {
      "at": "2026-06-06T05:04:51.656Z",
      "marketAverage": 172.5,
      "stationCount": 7
    },
    {
      "at": "2026-06-06T14:51:48.971Z",
      "marketAverage": 172.5,
      "stationCount": 7
    },
    {
      "at": "2026-06-06T16:21:33.356Z",
      "marketAverage": 172.5,
      "stationCount": 7
    },
    {
      "at": "2026-06-06T18:23:55.464Z",
      "marketAverage": 172,
      "stationCount": 7
    },
    {
      "at": "2026-06-06T20:15:09.282Z",
      "marketAverage": 172,
      "stationCount": 7
    },
    {
      "at": "2026-06-06T22:13:26.094Z",
      "marketAverage": 165.1,
      "stationCount": 5
    },
    {
      "at": "2026-06-07T05:28:13.805Z",
      "marketAverage": 164.3,
      "stationCount": 5
    },
    {
      "at": "2026-06-07T15:04:07.099Z",
      "marketAverage": 164.3,
      "stationCount": 5
    },
    {
      "at": "2026-06-07T16:26:25.716Z",
      "marketAverage": 165.1,
      "stationCount": 6
    },
    {
      "at": "2026-06-07T18:13:47.996Z",
      "marketAverage": 165.1,
      "stationCount": 6
    },
    {
      "at": "2026-06-07T20:25:22.834Z",
      "marketAverage": 164.2,
      "stationCount": 8
    },
    {
      "at": "2026-06-07T22:15:51.658Z",
      "marketAverage": 164.2,
      "stationCount": 8
    },
    {
      "at": "2026-06-08T00:26:22.684Z",
      "marketAverage": 164.2,
      "stationCount": 8
    },
    {
      "at": "2026-06-08T06:03:37.089Z",
      "marketAverage": 164.2,
      "stationCount": 8
    },
    {
      "at": "2026-06-08T17:05:17.038Z",
      "marketAverage": 163,
      "stationCount": 8
    },
    {
      "at": "2026-06-08T19:28:48.016Z",
      "marketAverage": 161,
      "stationCount": 8
    },
    {
      "at": "2026-06-08T21:56:32.729Z",
      "marketAverage": 160.8,
      "stationCount": 8
    },
    {
      "at": "2026-06-08T23:21:13.934Z",
      "marketAverage": 160.8,
      "stationCount": 8
    },
    {
      "at": "2026-06-09T16:13:46.180Z",
      "marketAverage": 172.8,
      "stationCount": 8
    },
    {
      "at": "2026-06-09T19:33:09.151Z",
      "marketAverage": 178.8,
      "stationCount": 8
    },
    {
      "at": "2026-06-09T23:28:28.797Z",
      "marketAverage": 181.9,
      "stationCount": 8
    },
    {
      "at": "2026-06-10T04:22:49.428Z",
      "marketAverage": 181.4,
      "stationCount": 8
    },
    {
      "at": "2026-06-10T16:44:55.080Z",
      "marketAverage": 181.4,
      "stationCount": 8
    },
    {
      "at": "2026-06-10T19:42:01.467Z",
      "marketAverage": 181.4,
      "stationCount": 8
    },
    {
      "at": "2026-06-10T22:09:44.641Z",
      "marketAverage": 181.4,
      "stationCount": 8
    },
    {
      "at": "2026-06-11T00:27:28.693Z",
      "marketAverage": 180.9,
      "stationCount": 8
    },
    {
      "at": "2026-06-11T06:03:43.530Z",
      "marketAverage": 180,
      "stationCount": 8
    },
    {
      "at": "2026-06-11T17:10:05.333Z",
      "marketAverage": 182.8,
      "stationCount": 8
    },
    {
      "at": "2026-06-11T19:53:06.059Z",
      "marketAverage": 181.9,
      "stationCount": 8
    },
    {
      "at": "2026-06-11T22:10:51.824Z",
      "marketAverage": 181.9,
      "stationCount": 8
    },
    {
      "at": "2026-06-12T00:34:56.368Z",
      "marketAverage": 181.9,
      "stationCount": 8
    },
    {
      "at": "2026-06-12T06:02:52.126Z",
      "marketAverage": 181.7,
      "stationCount": 8
    },
    {
      "at": "2026-06-12T16:33:06.142Z",
      "marketAverage": 181.7,
      "stationCount": 8
    },
    {
      "at": "2026-06-12T19:17:00.907Z",
      "marketAverage": 181.2,
      "stationCount": 8
    },
    {
      "at": "2026-06-12T22:04:59.796Z",
      "marketAverage": 179.9,
      "stationCount": 8
    },
    {
      "at": "2026-06-12T23:29:52.246Z",
      "marketAverage": 179.9,
      "stationCount": 8
    },
    {
      "at": "2026-06-13T04:27:07.682Z",
      "marketAverage": 179.4,
      "stationCount": 8
    },
    {
      "at": "2026-06-13T17:32:35.707Z",
      "marketAverage": 178.6,
      "stationCount": 7
    },
    {
      "at": "2026-06-13T19:55:16.325Z",
      "marketAverage": 178.9,
      "stationCount": 7
    },
    {
      "at": "2026-06-13T23:19:14.075Z",
      "marketAverage": 175.8,
      "stationCount": 7
    },
    {
      "at": "2026-06-14T04:45:54.092Z",
      "marketAverage": 175.8,
      "stationCount": 7
    },
    {
      "at": "2026-06-14T15:10:41.429Z",
      "marketAverage": 175.8,
      "stationCount": 7
    },
    {
      "at": "2026-06-14T17:35:19.628Z",
      "marketAverage": 175.8,
      "stationCount": 7
    },
    {
      "at": "2026-06-14T19:46:09.610Z",
      "marketAverage": 175.8,
      "stationCount": 7
    },
    {
      "at": "2026-06-14T21:33:24.739Z",
      "marketAverage": 175.8,
      "stationCount": 7
    },
    {
      "at": "2026-06-14T23:22:52.473Z",
      "marketAverage": 174.2,
      "stationCount": 8
    },
    {
      "at": "2026-06-15T05:10:23.383Z",
      "marketAverage": 173.2,
      "stationCount": 8
    },
    {
      "at": "2026-06-15T18:10:08.919Z",
      "marketAverage": 173.2,
      "stationCount": 8
    },
    {
      "at": "2026-06-15T21:26:51.015Z",
      "marketAverage": 173.2,
      "stationCount": 8
    },
    {
      "at": "2026-06-15T23:58:08.909Z",
      "marketAverage": 170.9,
      "stationCount": 8
    },
    {
      "at": "2026-06-16T05:03:45.156Z",
      "marketAverage": 170.7,
      "stationCount": 8
    },
    {
      "at": "2026-06-16T18:10:44.537Z",
      "marketAverage": 174.5,
      "stationCount": 8
    },
    {
      "at": "2026-06-16T21:43:55.063Z",
      "marketAverage": 176.5,
      "stationCount": 8
    },
    {
      "at": "2026-06-16T23:36:36.041Z",
      "marketAverage": 178.5,
      "stationCount": 8
    },
    {
      "at": "2026-06-17T04:59:13.578Z",
      "marketAverage": 178.3,
      "stationCount": 8
    },
    {
      "at": "2026-06-17T16:46:30.174Z",
      "marketAverage": 178.5,
      "stationCount": 8
    },
    {
      "at": "2026-06-17T19:29:10.346Z",
      "marketAverage": 178.3,
      "stationCount": 8
    },
    {
      "at": "2026-06-17T22:10:43.549Z",
      "marketAverage": 178.3,
      "stationCount": 8
    },
    {
      "at": "2026-06-18T00:32:22.188Z",
      "marketAverage": 177.8,
      "stationCount": 8
    }
  ]
}
